anki_packager/__init__.py
anki_packager/__main__.py
anki_packager/cli.py
anki_packager/logger.py
anki_packager/prompt.py
anki_packager/utils.py
anki_packager/ai/__init__.py
anki_packager/ai/gemini.py
anki_packager/ai/gpt.py
anki_packager/ai/siliconflow.py
anki_packager/dict/__init__.py
anki_packager/dict/ecdict.py
anki_packager/dict/eudic.py
anki_packager/dict/longman.py
anki_packager/dict/stardict.py
anki_packager/dict/youdao.py
anki_packager/packager/deck.py
apkger-0.9.5.dist-info/licenses/LICENSE
apkger-0.9.5.dist-info/METADATA
apkger-0.9.5.dist-info/WHEEL
apkger-0.9.5.dist-info/entry_points.txt
apkger-0.9.5.dist-info/top_level.txt
apkger-0.9.5.dist-info/RECORD
