Metadata-Version: 2.4
Name: apkger
Version: 0.9.5
Summary: 自动化 Anki 英语单词卡片牌组生成器
Home-page: https://github.com/yaoyhu/anki_packager
Author: Yaoyao Hu
Author-email: shady030314@gmail.com
Classifier: Programming Language :: Python :: 3
Classifier: Programming Language :: Python :: 3.9
Classifier: License :: OSI Approved :: MIT License
Classifier: Operating System :: OS Independent
Classifier: Topic :: Education
Classifier: Topic :: Text Processing :: Linguistic
Classifier: Development Status :: 4 - Beta
Requires-Python: >=3.9
License-File: LICENSE
Requires-Dist: beautifulsoup4==4.7.1
Requires-Dist: genanki==0.13.1
Requires-Dist: gTTS==2.5.3
Requires-Dist: openai==1.61.1
Requires-Dist: protobuf==5.29.3
Requires-Dist: Requests==2.32.3
Requires-Dist: google-genai==1.2.0
Requires-Dist: mdict-utils==1.3.14
Requires-Dist: py7zr==0.22.0
Requires-Dist: socksio==1.0.0
Dynamic: author
Dynamic: author-email
Dynamic: classifier
Dynamic: description
Dynamic: description-content-type
Dynamic: home-page
Dynamic: license-file
Dynamic: requires-dist
Dynamic: requires-python
Dynamic: summary
